strox/__init__.py
strox/__main__.py
strox/_cli.py
strox-0.1.5.dist-info/licenses/LICENSE
strox-0.1.5.dist-info/WHEEL
strox-0.1.5.dist-info/entry_points.txt
strox-0.1.5.dist-info/METADATA
strox-0.1.5.dist-info/RECORD
