Metadata-Version: 2.4
Name: strox
Version: 0.1.5
Summary: Find strings that matches approximately the given query
Author: Havsalt
Author-email: Havsalt <77575424+Havsalt@users.noreply.github.com>
License-Expression: MIT
License-File: LICENSE
Requires-Dist: rich-argparse~=1.7 ; extra == 'cli-color'
Requires-Python: >=3.10
Provides-Extra: cli-color
